{
"issues":  [
{
"id":  "S1128",
"message":  "Remove this unnecessary 'using'.",
"location":  {
"uri":  "sources\akka.net\src\core\Akka.Persistence\Journal\EventAdapters.cs",
"region":  {
"startLine":  12,
"startColumn":  1,
"endLine":  12,
"endColumn":  25
}
}
},
{
"id":  "S1128",
"message":  "Remove this unnecessary 'using'.",
"location":  {
"uri":  "sources\akka.net\src\core\Akka.Persistence\Journal\PersistencePluginProxy.cs",
"region":  {
"startLine":  14,
"startColumn":  1,
"endLine":  14,
"endColumn":  26
}
}
},
{
"id":  "S1128",
"message":  "Remove this unnecessary 'using'.",
"location":  {
"uri":  "sources\akka.net\src\core\Akka.Persistence\Persistence.cs",
"region":  {
"startLine":  11,
"startColumn":  1,
"endLine":  11,
"endColumn":  25
}
}
},
{
"id":  "S1128",
"message":  "Remove this unnecessary 'using'.",
"location":  {
"uri":  "sources\akka.net\src\core\Akka.Persistence\Properties\AssemblyInfo.cs",
"region":  {
"startLine":  8,
"startColumn":  1,
"endLine":  8,
"endColumn":  25
}
}
},
{
"id":  "S1128",
"message":  "Remove this unnecessary 'using'.",
"location":  {
"uri":  "sources\akka.net\src\core\Akka.Persistence\Serialization\IMessage.cs",
"region":  {
"startLine":  8,
"startColumn":  1,
"endLine":  8,
"endColumn":  14
}
}
},
{
"id":  "S1128",
"message":  "Remove this unnecessary 'using'.",
"location":  {
"uri":  "sources\akka.net\src\core\Akka.Persistence\Serialization\IMessage.cs",
"region":  {
"startLine":  9,
"startColumn":  1,
"endLine":  9,
"endColumn":  34
}
}
},
{
"id":  "S1128",
"message":  "Remove this unnecessary 'using'.",
"location":  {
"uri":  "sources\akka.net\src\core\Akka.Persistence\Serialization\IMessage.cs",
"region":  {
"startLine":  10,
"startColumn":  1,
"endLine":  10,
"endColumn":  36
}
}
},
{
"id":  "S1128",
"message":  "Remove this unnecessary 'using'.",
"location":  {
"uri":  "sources\akka.net\src\core\Akka.Persistence\Serialization\IMessage.cs",
"region":  {
"startLine":  11,
"startColumn":  1,
"endLine":  11,
"endColumn":  19
}
}
},
{
"id":  "S1128",
"message":  "Remove this unnecessary 'using'.",
"location":  {
"uri":  "sources\akka.net\src\core\Akka.Persistence\Serialization\IMessage.cs",
"region":  {
"startLine":  12,
"startColumn":  1,
"endLine":  12,
"endColumn":  18
}
}
},
{
"id":  "S1128",
"message":  "Remove this unnecessary 'using'.",
"location":  {
"uri":  "sources\akka.net\src\core\Akka.Persistence\Serialization\IMessage.cs",
"region":  {
"startLine":  13,
"startColumn":  1,
"endLine":  13,
"endColumn":  26
}
}
},
{
"id":  "S1128",
"message":  "Remove this unnecessary 'using'.",
"location":  {
"uri":  "sources\akka.net\src\core\Akka.Persistence\Serialization\IMessage.cs",
"region":  {
"startLine":  14,
"startColumn":  1,
"endLine":  14,
"endColumn":  17
}
}
},
{
"id":  "S1128",
"message":  "Remove this unnecessary 'using'.",
"location":  {
"uri":  "sources\akka.net\src\core\Akka.Persistence\Serialization\PersistenceMessageSerializer.cs",
"region":  {
"startLine":  17,
"startColumn":  1,
"endLine":  17,
"endColumn":  17
}
}
},
{
"id":  "S1128",
"message":  "Remove this unnecessary 'using'.",
"location":  {
"uri":  "sources\akka.net\src\core\Akka.Persistence\Serialization\Snapshot.cs",
"region":  {
"startLine":  9,
"startColumn":  1,
"endLine":  9,
"endColumn":  17
}
}
},
{
"id":  "S1128",
"message":  "Remove this unnecessary 'using'.",
"location":  {
"uri":  "sources\akka.net\src\core\Akka.Persistence\Serialization\Snapshot.cs",
"region":  {
"startLine":  10,
"startColumn":  1,
"endLine":  10,
"endColumn":  19
}
}
},
{
"id":  "S1128",
"message":  "Remove this unnecessary 'using'.",
"location":  {
"uri":  "sources\akka.net\src\core\Akka.Persistence\Serialization\Snapshot.cs",
"region":  {
"startLine":  11,
"startColumn":  1,
"endLine":  11,
"endColumn":  18
}
}
},
{
"id":  "S1128",
"message":  "Remove this unnecessary 'using'.",
"location":  {
"uri":  "sources\akka.net\src\core\Akka.Persistence\Serialization\Snapshot.cs",
"region":  {
"startLine":  12,
"startColumn":  1,
"endLine":  12,
"endColumn":  26
}
}
},
{
"id":  "S1128",
"message":  "Remove this unnecessary 'using'.",
"location":  {
"uri":  "sources\akka.net\src\core\Akka.Persistence\Serialization\Snapshot.cs",
"region":  {
"startLine":  13,
"startColumn":  1,
"endLine":  13,
"endColumn":  17
}
}
},
{
"id":  "S1128",
"message":  "Remove this unnecessary 'using'.",
"location":  {
"uri":  "sources\akka.net\src\core\Akka.Persistence\Snapshotter.cs",
"region":  {
"startLine":  8,
"startColumn":  1,
"endLine":  8,
"endColumn":  14
}
}
}
]
}
