{
"issues":  [
{
"id":  "S1144",
"message":  "Remove the unused private field '_cluster'.",
"location":  {
"uri":  "sources\akka.net\src\contrib\cluster\Akka.Cluster.Sharding\ClusterShardingGuardian.cs",
"region":  {
"startLine":  81,
"startColumn":  9,
"endLine":  81,
"endColumn":  73
}
}
},
{
"id":  "S1144",
"message":  "Remove the unused private field '_sharding'.",
"location":  {
"uri":  "sources\akka.net\src\contrib\cluster\Akka.Cluster.Sharding\ClusterShardingGuardian.cs",
"region":  {
"startLine":  82,
"startColumn":  9,
"endLine":  82,
"endColumn":  90
}
}
}
]
}
