{
"issues":  [
{
"id":  "S6563",
"message":  "Use UTC when recoding DateTime instants",
"location":  {
"uri":  "https://github.com/SonarSource/sonar-dotnet/blob/master/analyzers/its/sources/akka.net/src/contrib/cluster/Akka.Cluster.Sharding/Shard.cs#L832",
"region":  {
"startLine":  832,
"startColumn":  85,
"endLine":  832,
"endColumn":  97
}
}
},
{
"id":  "S6563",
"message":  "Use UTC when recoding DateTime instants",
"location":  {
"uri":  "https://github.com/SonarSource/sonar-dotnet/blob/master/analyzers/its/sources/akka.net/src/contrib/cluster/Akka.Cluster.Sharding/Shard.cs#L839",
"region":  {
"startLine":  839,
"startColumn":  28,
"endLine":  839,
"endColumn":  40
}
}
}
]
}
