{
  "Issues": [
    {
      "Id": "S1481",
      "Message": "Remove the unused local variable \u0027discoveryComplete\u0027.",
      "Uri": "https://github.com/SonarSource/sonar-dotnet/blob/master/analyzers/its/Projects/akka.net/src/core/Akka.MultiNodeTestRunner/Discovery.cs#L59",
      "Location": "Line 59 Position 48-65"
    },
    {
      "Id": "S1481",
      "Message": "Remove the unused local variable \u0027alternateIndex\u0027.",
      "Uri": "https://github.com/SonarSource/sonar-dotnet/blob/master/analyzers/its/Projects/akka.net/src/core/Akka.MultiNodeTestRunner/Program.cs#L294",
      "Location": "Line 294 Position 33-47"
    }
  ]
}