{
"issues":  [
{
"id":  "S134",
"message":  "Refactor this code to not nest more than 3 control flow statements.",
"location":  {
"uri":  "sources\akka.net\src\contrib\cluster\Akka.Cluster.Tools\PublishSubscribe\DistributedPubSubMediator.cs",
"region":  {
"startLine":  162,
"startColumn":  29,
"endLine":  162,
"endColumn":  31
}
}
},
{
"id":  "S134",
"message":  "Refactor this code to not nest more than 3 control flow statements.",
"location":  {
"uri":  "sources\akka.net\src\contrib\cluster\Akka.Cluster.Tools\PublishSubscribe\DistributedPubSubMediator.cs",
"region":  {
"startLine":  275,
"startColumn":  29,
"endLine":  275,
"endColumn":  31
}
}
},
{
"id":  "S134",
"message":  "Refactor this code to not nest more than 3 control flow statements.",
"location":  {
"uri":  "sources\akka.net\src\contrib\cluster\Akka.Cluster.Tools\PublishSubscribe\DistributedPubSubMediator.cs",
"region":  {
"startLine":  278,
"startColumn":  29,
"endLine":  278,
"endColumn":  31
}
}
},
{
"id":  "S134",
"message":  "Refactor this code to not nest more than 3 control flow statements.",
"location":  {
"uri":  "sources\akka.net\src\contrib\cluster\Akka.Cluster.Tools\PublishSubscribe\DistributedPubSubMediator.cs",
"region":  {
"startLine":  403,
"startColumn":  25,
"endLine":  403,
"endColumn":  27
}
}
},
{
"id":  "S134",
"message":  "Refactor this code to not nest more than 3 control flow statements.",
"location":  {
"uri":  "sources\akka.net\src\contrib\cluster\Akka.Cluster.Tools\Singleton\ClusterSingletonManager.cs",
"region":  {
"startLine":  475,
"startColumn":  33,
"endLine":  475,
"endColumn":  35
}
}
},
{
"id":  "S134",
"message":  "Refactor this code to not nest more than 3 control flow statements.",
"location":  {
"uri":  "sources\akka.net\src\contrib\cluster\Akka.Cluster.Tools\Singleton\ClusterSingletonManager.cs",
"region":  {
"startLine":  487,
"startColumn":  33,
"endLine":  487,
"endColumn":  35
}
}
}
]
}
