{
"issues":  [
{
"id":  "S3052",
"message":  "Remove this initialization to '_failed', the compiler will do that for you.",
"location":  {
"uri":  "sources\akka.net\src\core\Akka.Remote.TestKit\BarrierCoordinator.cs",
"region":  {
"startLine":  385,
"startColumn":  30,
"endLine":  385,
"endColumn":  37
}
}
},
{
"id":  "S3052",
"message":  "Remove this initialization to '_commonConf', the compiler will do that for you.",
"location":  {
"uri":  "sources\akka.net\src\core\Akka.Remote.TestKit\MultiNodeSpec.cs",
"region":  {
"startLine":  31,
"startColumn":  28,
"endLine":  31,
"endColumn":  34
}
}
},
{
"id":  "S3052",
"message":  "Remove this initialization to '_testTransport', the compiler will do that for you.",
"location":  {
"uri":  "sources\akka.net\src\core\Akka.Remote.TestKit\MultiNodeSpec.cs",
"region":  {
"startLine":  36,
"startColumn":  29,
"endLine":  36,
"endColumn":  36
}
}
},
{
"id":  "S3052",
"message":  "Remove this initialization to '_loggedDisconnect', the compiler will do that for you.",
"location":  {
"uri":  "sources\akka.net\src\core\Akka.Remote.TestKit\Player.cs",
"region":  {
"startLine":  526,
"startColumn":  40,
"endLine":  526,
"endColumn":  47
}
}
}
]
}
